{
    "version": "https://jsonfeed.org/version/1",
    "title": "Hexo",
    "description": "",
    "home_page_url": "http://example.com",
    "items": [
        {
            "id": "http://example.com/2024/10/17/hello-world/",
            "url": "http://example.com/2024/10/17/hello-world/",
            "title": "Hello World",
            "date_published": "2024-10-17T13:57:36.990Z",
            "content_html": "<p>Welcome to <span class=\"exturl\"><a class=\"exturl__link\"   href=\"https://hexo.io/\" >Hexo</a><span class=\"exturl__icon\"><i class=\"fas fa-external-link-alt\"></i></span></span>! This is your very first post. Check <span class=\"exturl\"><a class=\"exturl__link\"   href=\"https://hexo.io/docs/\" >documentation</a><span class=\"exturl__icon\"><i class=\"fas fa-external-link-alt\"></i></span></span> for more info. If you get any problems when using Hexo, you can find the answer in <span class=\"exturl\"><a class=\"exturl__link\"   href=\"https://hexo.io/docs/troubleshooting.html\" >troubleshooting</a><span class=\"exturl__icon\"><i class=\"fas fa-external-link-alt\"></i></span></span> or you can ask me on <span class=\"exturl\"><a class=\"exturl__link\"   href=\"https://github.com/hexojs/hexo/issues\" >GitHub</a><span class=\"exturl__icon\"><i class=\"fas fa-external-link-alt\"></i></span></span>.</p>\n\n        <h2 id=\"quick-start\"   >\n          <a href=\"#quick-start\" class=\"heading-link\"><i class=\"fas fa-link\"></i></a><a class=\"markdownIt-Anchor\" href=\"#quick-start\">#</a> Quick Start</h2>\n      \n\n        <h3 id=\"create-a-new-post\"   >\n          <a href=\"#create-a-new-post\" class=\"heading-link\"><i class=\"fas fa-link\"></i></a><a class=\"markdownIt-Anchor\" href=\"#create-a-new-post\">#</a> Create a new post</h3>\n      \n<figure class=\"highlight bash\"><div class=\"table-container\"><table><tr><td class=\"gutter\"><pre><span class=\"line\">1</span><br></pre></td><td class=\"code\"><pre><span class=\"line\">$ hexo new <span class=\"string\">&quot;My New Post&quot;</span></span><br></pre></td></tr></table></div></figure>\n<p>More info: <span class=\"exturl\"><a class=\"exturl__link\"   href=\"https://hexo.io/docs/writing.html\" >Writing</a><span class=\"exturl__icon\"><i class=\"fas fa-external-link-alt\"></i></span></span></p>\n\n        <h3 id=\"run-server\"   >\n          <a href=\"#run-server\" class=\"heading-link\"><i class=\"fas fa-link\"></i></a><a class=\"markdownIt-Anchor\" href=\"#run-server\">#</a> Run server</h3>\n      \n<figure class=\"highlight bash\"><div class=\"table-container\"><table><tr><td class=\"gutter\"><pre><span class=\"line\">1</span><br></pre></td><td class=\"code\"><pre><span class=\"line\">$ hexo server</span><br></pre></td></tr></table></div></figure>\n<p>More info: <span class=\"exturl\"><a class=\"exturl__link\"   href=\"https://hexo.io/docs/server.html\" >Server</a><span class=\"exturl__icon\"><i class=\"fas fa-external-link-alt\"></i></span></span></p>\n\n        <h3 id=\"generate-static-files\"   >\n          <a href=\"#generate-static-files\" class=\"heading-link\"><i class=\"fas fa-link\"></i></a><a class=\"markdownIt-Anchor\" href=\"#generate-static-files\">#</a> Generate static files</h3>\n      \n<figure class=\"highlight bash\"><div class=\"table-container\"><table><tr><td class=\"gutter\"><pre><span class=\"line\">1</span><br></pre></td><td class=\"code\"><pre><span class=\"line\">$ hexo generate</span><br></pre></td></tr></table></div></figure>\n<p>More info: <span class=\"exturl\"><a class=\"exturl__link\"   href=\"https://hexo.io/docs/generating.html\" >Generating</a><span class=\"exturl__icon\"><i class=\"fas fa-external-link-alt\"></i></span></span></p>\n\n        <h3 id=\"deploy-to-remote-sites\"   >\n          <a href=\"#deploy-to-remote-sites\" class=\"heading-link\"><i class=\"fas fa-link\"></i></a><a class=\"markdownIt-Anchor\" href=\"#deploy-to-remote-sites\">#</a> Deploy to remote sites</h3>\n      \n<figure class=\"highlight bash\"><div class=\"table-container\"><table><tr><td class=\"gutter\"><pre><span class=\"line\">1</span><br></pre></td><td class=\"code\"><pre><span class=\"line\">$ hexo deploy</span><br></pre></td></tr></table></div></figure>\n<p>More info: <span class=\"exturl\"><a class=\"exturl__link\"   href=\"https://hexo.io/docs/one-command-deployment.html\" >Deployment</a><span class=\"exturl__icon\"><i class=\"fas fa-external-link-alt\"></i></span></span></p>\n",
            "tags": []
        }
    ]
}